robustbase/__init__.py
robustbase/auxiliary.py
robustbase/fast_s.py
robustbase/lmrob.py
robustbase/psi.py
robustbase_py_optimized-0.1.1.dist-info/licenses/LICENSE
robustbase_py_optimized-0.1.1.dist-info/METADATA
robustbase_py_optimized-0.1.1.dist-info/WHEEL
robustbase_py_optimized-0.1.1.dist-info/top_level.txt
robustbase_py_optimized-0.1.1.dist-info/RECORD
