Metadata-Version: 2.4
Name: robustbase-py-optimized
Version: 0.1.1
Summary: A Python port of the R robustbase package with optimized performance using JAX
Author: Eichi Uehara
License:                     GNU GENERAL PUBLIC LICENSE
Project-URL: Homepage, https://github.com/EichiUehara/robustbase-py
Classifier: Programming Language :: Python :: 3
Classifier: License :: OSI Approved :: GNU General Public License v3 (GPLv3)
Classifier: Operating System :: OS Independent
Requires-Python: >=3.8
License-File: LICENSE
Requires-Dist: numpy
Requires-Dist: jax
Requires-Dist: jaxlib
Dynamic: license-file
